mofun/__init__.py
mofun/atomic_masses.py
mofun/atoms.py
mofun/helpers.py
mofun/mofun.py
mofun/raspa_output.py
mofun/rough_uff.py
mofun/uff4mof.py
mofun/cli/__init__.py
mofun/cli/mofun_cli.py
mofun-1.0.dist-info/LICENSE
mofun-1.0.dist-info/METADATA
mofun-1.0.dist-info/WHEEL
mofun-1.0.dist-info/entry_points.txt
mofun-1.0.dist-info/top_level.txt
mofun-1.0.dist-info/RECORD
