Metadata-Version: 2.1
Name: mofun
Version: 1.0
Summary: Find and replace functional groups in any given periodic structure.
Home-page: https://github.com/wilmerlab/mofun.git
Author: Paul Boone
Author-email: narcissus.pong@gmail.com
License: UNKNOWN
Platform: UNKNOWN
License-File: LICENSE
Requires-Dist: ase
Requires-Dist: numpy
Requires-Dist: scipy
Requires-Dist: PyCifRW
Requires-Dist: networkx
Requires-Dist: click
Requires-Dist: ordered-set
Provides-Extra: docs
Requires-Dist: mkdocs-material ; extra == 'docs'
Requires-Dist: mkdocstrings ; extra == 'docs'
